<?xml version="1.0" encoding="utf-8"?>
<AdditionalInfo>
  <CTypeInfo>
      <RtlPort>
        <name>s_axi_CPU_ARADDR</name>
        <type>Unsigned</type>
        <fractionWidth>0</fractionWidth>
      </RtlPort>
      <RtlPort>
        <name>s_axi_CPU_ARREADY</name>
        <type>Unsigned</type>
        <fractionWidth>0</fractionWidth>
      </RtlPort>
      <RtlPort>
        <name>s_axi_CPU_ARVALID</name>
        <type>Unsigned</type>
        <fractionWidth>0</fractionWidth>
      </RtlPort>
      <RtlPort>
        <name>s_axi_CPU_AWADDR</name>
        <type>Unsigned</type>
        <fractionWidth>0</fractionWidth>
      </RtlPort>
      <RtlPort>
        <name>s_axi_CPU_AWREADY</name>
        <type>Unsigned</type>
        <fractionWidth>0</fractionWidth>
      </RtlPort>
      <RtlPort>
        <name>s_axi_CPU_AWVALID</name>
        <type>Unsigned</type>
        <fractionWidth>0</fractionWidth>
      </RtlPort>
      <RtlPort>
        <name>s_axi_CPU_BREADY</name>
        <type>Unsigned</type>
        <fractionWidth>0</fractionWidth>
      </RtlPort>
      <RtlPort>
        <name>s_axi_CPU_BRESP</name>
        <type>Unsigned</type>
        <fractionWidth>0</fractionWidth>
      </RtlPort>
      <RtlPort>
        <name>s_axi_CPU_BVALID</name>
        <type>Unsigned</type>
        <fractionWidth>0</fractionWidth>
      </RtlPort>
      <RtlPort>
        <name>s_axi_CPU_RDATA</name>
        <type>Unsigned</type>
        <fractionWidth>0</fractionWidth>
      </RtlPort>
      <RtlPort>
        <name>s_axi_CPU_RREADY</name>
        <type>Unsigned</type>
        <fractionWidth>0</fractionWidth>
      </RtlPort>
      <RtlPort>
        <name>s_axi_CPU_RRESP</name>
        <type>Unsigned</type>
        <fractionWidth>0</fractionWidth>
      </RtlPort>
      <RtlPort>
        <name>s_axi_CPU_RVALID</name>
        <type>Unsigned</type>
        <fractionWidth>0</fractionWidth>
      </RtlPort>
      <RtlPort>
        <name>s_axi_CPU_WDATA</name>
        <type>Unsigned</type>
        <fractionWidth>0</fractionWidth>
      </RtlPort>
      <RtlPort>
        <name>s_axi_CPU_WREADY</name>
        <type>Unsigned</type>
        <fractionWidth>0</fractionWidth>
      </RtlPort>
      <RtlPort>
        <name>s_axi_CPU_WSTRB</name>
        <type>Unsigned</type>
        <fractionWidth>0</fractionWidth>
      </RtlPort>
      <RtlPort>
        <name>s_axi_CPU_WVALID</name>
        <type>Unsigned</type>
        <fractionWidth>0</fractionWidth>
      </RtlPort>
      <RtlPort>
        <name>sample_cnt_target_out</name>
        <type>Unsigned</type>
        <fractionWidth>0</fractionWidth>
      </RtlPort>
  </CTypeInfo>
  <DesignConstraint>
    <clk_period>10</clk_period>
  </DesignConstraint>
  <Machine>64</Machine>
  <modelParameters>
    <combinational>1</combinational>
    <latency>0</latency>
    <II>x</II>
  </modelParameters>
</AdditionalInfo>
